MANIFEST.in
README.rst
requirements.txt
setup.cfg
setup.py
pyicloud/__init__.py
pyicloud/base.py
pyicloud/cmdline.py
pyicloud/exceptions.py
pyicloud/utils.py
pyicloud/services/__init__.py
pyicloud/services/reminders.py
pyicloud/tests/__init__.py
pyicloud/tests/test_sanity.py
pyicloudreminders.egg-info/PKG-INFO
pyicloudreminders.egg-info/SOURCES.txt
pyicloudreminders.egg-info/dependency_links.txt
pyicloudreminders.egg-info/entry_points.txt
pyicloudreminders.egg-info/requires.txt
pyicloudreminders.egg-info/top_level.txt