Metadata-Version: 1.1
Name: pyicloudreminders
Version: 0.1.1
Summary: PyiCloudReminders is a module (a fork of pyicloud) whichallows pythonistas to interact with iCloud Reminders.
Home-page: https://github.com/coumbole/pyicloudreminders
Author: The PyiCloud + PyiCloudReminders Authors
Author-email: ville@kumpulainen.org
License: MIT
Platform: UNKNOWN
Classifier: Intended Audience :: Developers
Classifier: Operating System :: OS Independent
Classifier: Programming Language :: Python
Classifier: Programming Language :: Python :: 2.6
Classifier: Programming Language :: Python :: 2.7
Classifier: Programming Language :: Python :: 3
Classifier: License :: OSI Approved :: MIT License
